{
  "DocumentMetadata": {
    "Pages": 1
  },
  "ExpenseDocuments": [
    {
      "ExpenseIndex": 1,
      "SummaryFields": [
        {
          "Type": {
            "Text": "ADDRESS",
            "Confidence": 99.99092864990234
          },
          "ValueDetection": {
            "Text": "RESTAURANT SIN DU\nK3-113, JL IBRAHIM SULTAN\n80300 JOHOR BAHRU\nJOHOR",
            "Geometry": {
              "BoundingBox": {
                "Width": 0.1713709980249405,
                "Height": 0.05085686966776848,
                "Left": 0.3114751875400543,
                "Top": 0.2536396384239197
              },
              "Polygon": [
                {
                  "X": 0.3114751875400543,
                  "Y": 0.2544710636138916
                },
                {
                  "X": 0.48278388381004333,
                  "Y": 0.2536396384239197
                },
                {
                  "X": 0.482846200466156,
                  "Y": 0.303579181432724
                },
                {
                  "X": 0.3115234076976776,
                  "Y": 0.30449649691581726
                }
              ]
            },
            "Confidence": 99.7420883178711
          },
          "PageNumber": 1,
          "GroupProperties": [
            {
              "Types": [
                "VENDOR"
              ],
              "Id": "77a35cd6-024c-4dda-9dc7-4910a6cf9fe7"
            }
          ]
        },
        {
          "Type": {
            "Text": "STREET",
            "Confidence": 99.99092864990234
          },
          "ValueDetection": {
            "Text": "K3-113, JL IBRAHIM SULTAN",
            "Geometry": {
              "BoundingBox": {
                "Width": 0.17143318057060242,
                "Height": 0.014959851279854774,
                "Left": 0.31138333678245544,
                "Top": 0.2657278776168823
              },
              "Polygon": [
                {
                  "X": 0.31138333678245544,
                  "Y": 0.26658061146736145
                },
                {
                  "X": 0.4827989637851715,
                  "Y": 0.2657278776168823
                },
                {
                  "X": 0.48281654715538025,
                  "Y": 0.27981075644493103
                },
                {
                  "X": 0.31139692664146423,
                  "Y": 0.28068774938583374
                }
              ]
            },
            "Confidence": 99.44493103027344
          },
          "PageNumber": 1,
          "GroupProperties": [
            {
              "Types": [
                "VENDOR"
              ],
              "Id": "77a35cd6-024c-4dda-9dc7-4910a6cf9fe7"
            }
          ]
        },
        {
          "Type": {
            "Text": "CITY",
            "Confidence": 99.99092864990234
          },
          "ValueDetection": {
            "Text": "JOHOR BAHRU",
            "Geometry": {
              "BoundingBox": {
                "Width": 0.07951300591230392,
                "Height": 0.012302220799028873,
                "Left": 0.3817431926727295,
                "Top": 0.2799418866634369
              },
              "Polygon": [
                {
                  "X": 0.3817431926727295,
                  "Y": 0.28034859895706177
                },
                {
                  "X": 0.46124178171157837,
                  "Y": 0.2799418866634369
                },
                {
                  "X": 0.4612561762332916,
                  "Y": 0.29182788729667664
                },
                {
                  "X": 0.3817560374736786,
                  "Y": 0.2922441065311432
                }
              ]
            },
            "Confidence": 99.98431396484375
          },
          "PageNumber": 1,
          "GroupProperties": [
            {
              "Types": [
                "VENDOR"
              ],
              "Id": "77a35cd6-024c-4dda-9dc7-4910a6cf9fe7"
            }
          ]
        },
        {
          "Type": {
            "Text": "STATE",
            "Confidence": 99.99092864990234
          },
          "ValueDetection": {
            "Text": "JOHOR",
            "Geometry": {
              "BoundingBox": {
                "Width": 0.03737357631325722,
                "Height": 0.011865989305078983,
                "Left": 0.38075196743011475,
                "Top": 0.2922597825527191
              },
              "Polygon": [
                {
                  "X": 0.38075196743011475,
                  "Y": 0.29245543479919434
                },
                {
                  "X": 0.41811224818229675,
                  "Y": 0.2922597825527191
                },
                {
                  "X": 0.41812554001808167,
                  "Y": 0.3039257228374481
                },
                {
                  "X": 0.38076454401016235,
                  "Y": 0.30412575602531433
                }
              ]
            },
            "Confidence": 95.94973754882812
          },
          "PageNumber": 1,
          "GroupProperties": [
            {
              "Types": [
                "VENDOR"
              ],
              "Id": "77a35cd6-024c-4dda-9dc7-4910a6cf9fe7"
            }
          ]
        },
        {
          "Type": {
            "Text": "ZIP_CODE",
            "Confidence": 99.99092864990234
          },
          "ValueDetection": {
            "Text": "80300",
            "Geometry": {
              "BoundingBox": {
                "Width": 0.03708771616220474,
                "Height": 0.01175060123205185,
                "Left": 0.3385412395000458,
                "Top": 0.279371440410614
              },
              "Polygon": [
                {
                  "X": 0.3385412395000458,
                  "Y": 0.27956074476242065
                },
                {
                  "X": 0.37561658024787903,
                  "Y": 0.279371440410614
                },
                {
                  "X": 0.3756289482116699,
                  "Y": 0.2909284234046936
                },
                {
                  "X": 0.33855289220809937,
                  "Y": 0.2911220192909241
                }
              ]
            },
            "Confidence": 99.99641418457031
          },
          "PageNumber": 1,
          "GroupProperties": [
            {
              "Types": [
                "VENDOR"
              ],
              "Id": "77a35cd6-024c-4dda-9dc7-4910a6cf9fe7"
            }
          ]
        },
        {
          "Type": {
            "Text": "NAME",
            "Confidence": 99.78314971923828
          },
          "ValueDetection": {
            "Text": "RESTAURANT SIN DU",
            "Geometry": {
              "BoundingBox": {
                "Width": 0.12216874957084656,
                "Height": 0.013387774117290974,
                "Left": 0.3328000605106354,
                "Top": 0.254118412733078
              },
              "Polygon": [
                {
                  "X": 0.3328000605106354,
                  "Y": 0.25471168756484985
                },
                {
                  "X": 0.4549534320831299,
                  "Y": 0.254118412733078
                },
                {
                  "X": 0.45496881008148193,
                  "Y": 0.2668972313404083
                },
                {
                  "X": 0.3328128457069397,
                  "Y": 0.2675061821937561
                }
              ]
            },
            "Confidence": 99.61408233642578
          },
          "PageNumber": 1,
          "GroupProperties": [
            {
              "Types": [
                "VENDOR"
              ],
              "Id": "77a35cd6-024c-4dda-9dc7-4910a6cf9fe7"
            }
          ]
        },
        {
          "Type": {
            "Text": "ADDRESS_BLOCK",
            "Confidence": 99.78314971923828
          },
          "ValueDetection": {
            "Text": "K3-113, JL IBRAHIM SULTAN\n80300 JOHOR BAHRU\nJOHOR",
            "Geometry": {
              "BoundingBox": {
                "Width": 0.17146283388137817,
                "Height": 0.03876917064189911,
                "Left": 0.31138333678245544,
                "Top": 0.2657278776168823
              },
              "Polygon": [
                {
                  "X": 0.31138333678245544,
                  "Y": 0.26658061146736145
                },
                {
                  "X": 0.4827989637851715,
                  "Y": 0.2657278776168823
                },
                {
                  "X": 0.482846200466156,
                  "Y": 0.303579181432724
                },
                {
                  "X": 0.31141987442970276,
                  "Y": 0.3044970631599426
                }
              ]
            },
            "Confidence": 98.69239807128906
          },
          "PageNumber": 1,
          "GroupProperties": [
            {
              "Types": [
                "VENDOR"
              ],
              "Id": "77a35cd6-024c-4dda-9dc7-4910a6cf9fe7"
            }
          ]
        },
        {
          "Type": {
            "Text": "INVOICE_RECEIPT_DATE",
            "Confidence": 99.98866271972656
          },
          "ValueDetection": {
            "Text": "09/03/2018",
            "Geometry": {
              "BoundingBox": {
                "Width": 0.07262727618217468,
                "Height": 0.01202427688986063,
                "Left": 0.308560311794281,
                "Top": 0.34189340472221375
              },
              "Polygon": [
                {
                  "X": 0.308560311794281,
                  "Y": 0.34230971336364746
                },
                {
                  "X": 0.38117507100105286,
                  "Y": 0.34189340472221375
                },
                {
                  "X": 0.3811875879764557,
                  "Y": 0.35349294543266296
                },
                {
                  "X": 0.308571457862854,
                  "Y": 0.3539176881313324
                }
              ]
            },
            "Confidence": 99.98658752441406
          },
          "PageNumber": 1
        },
        {
          "Type": {
            "Text": "INVOICE_RECEIPT_ID",
            "Confidence": 97.23076629638672
          },
          "ValueDetection": {
            "Text": "0001",
            "Geometry": {
              "BoundingBox": {
                "Width": 0.02816607803106308,
                "Height": 0.0112706134095788,
                "Left": 0.45053550601005554,
                "Top": 0.34330764412879944
              },
              "Polygon": [
                {
                  "X": 0.45053550601005554,
                  "Y": 0.3434695899486542
                },
                {
                  "X": 0.4786877930164337,
                  "Y": 0.34330764412879944
                },
                {
                  "X": 0.4787015914916992,
                  "Y": 0.35441315174102783
                },
                {
                  "X": 0.45054876804351807,
                  "Y": 0.35457825660705566
                }
              ]
            },
            "Confidence": 97.22749328613281
          },
          "PageNumber": 1
        },
        {
          "Type": {
            "Text": "INVOICE_RECEIPT_ID",
            "Confidence": 71.3950424194336
          },
          "ValueDetection": {
            "Text": "000000#7259",
            "Geometry": {
              "BoundingBox": {
                "Width": 0.07946312427520752,
                "Height": 0.011712279170751572,
                "Left": 0.3083656132221222,
                "Top": 0.354602187871933
              },
              "Polygon": [
                {
                  "X": 0.3083656132221222,
                  "Y": 0.3550678491592407
                },
                {
                  "X": 0.38781648874282837,
                  "Y": 0.354602187871933
                },
                {
                  "X": 0.3878287374973297,
                  "Y": 0.3658398687839508
                },
                {
                  "X": 0.30837640166282654,
                  "Y": 0.36631447076797485
                }
              ]
            },
            "Confidence": 71.39349365234375
          },
          "PageNumber": 1
        },
        {
          "Type": {
            "Text": "TOTAL",
            "Confidence": 99.92882537841797
          },
          "LabelDetection": {
            "Text": "CASH",
            "Geometry": {
              "BoundingBox": {
                "Width": 0.03638608008623123,
                "Height": 0.01104824524372816,
                "Left": 0.3072661757469177,
                "Top": 0.4170820415019989
              },
              "Polygon": [
                {
                  "X": 0.3072661757469177,
                  "Y": 0.4173179268836975
                },
                {
                  "X": 0.3436412811279297,
                  "Y": 0.4170820415019989
                },
                {
                  "X": 0.34365224838256836,
                  "Y": 0.42789047956466675
                },
                {
                  "X": 0.30727651715278625,
                  "Y": 0.42813029885292053
                }
              ]
            },
            "Confidence": 99.92818450927734
          },
          "ValueDetection": {
            "Text": "RM 170.00",
            "Geometry": {
              "BoundingBox": {
                "Width": 0.1428050696849823,
                "Height": 0.013864303007721901,
                "Left": 0.3204685151576996,
                "Top": 0.42883267998695374
              },
              "Polygon": [
                {
                  "X": 0.3204685151576996,
                  "Y": 0.42977651953697205
                },
                {
                  "X": 0.46325790882110596,
                  "Y": 0.42883267998695374
                },
                {
                  "X": 0.4632735848426819,
                  "Y": 0.4417346715927124
                },
                {
                  "X": 0.32048115134239197,
                  "Y": 0.4426969885826111
                }
              ]
            },
            "Confidence": 99.92172241210938
          },
          "PageNumber": 1
        },
        {
          "Type": {
            "Text": "VENDOR_ADDRESS",
            "Confidence": 99.99092864990234
          },
          "ValueDetection": {
            "Text": "RESTAURANT SIN DU\nK3-113, JL IBRAHIM SULTAN\n80300 JOHOR BAHRU\nJOHOR",
            "Geometry": {
              "BoundingBox": {
                "Width": 0.1713709980249405,
                "Height": 0.05085686966776848,
                "Left": 0.3114751875400543,
                "Top": 0.2536396384239197
              },
              "Polygon": [
                {
                  "X": 0.3114751875400543,
                  "Y": 0.2544710636138916
                },
                {
                  "X": 0.48278388381004333,
                  "Y": 0.2536396384239197
                },
                {
                  "X": 0.482846200466156,
                  "Y": 0.303579181432724
                },
                {
                  "X": 0.3115234076976776,
                  "Y": 0.30449649691581726
                }
              ]
            },
            "Confidence": 99.7420883178711
          },
          "PageNumber": 1
        },
        {
          "Type": {
            "Text": "VENDOR_NAME",
            "Confidence": 99.78314971923828
          },
          "ValueDetection": {
            "Text": "RESTAURANT SIN DU",
            "Geometry": {
              "BoundingBox": {
                "Width": 0.12216874957084656,
                "Height": 0.013387774117290974,
                "Left": 0.3328000605106354,
                "Top": 0.254118412733078
              },
              "Polygon": [
                {
                  "X": 0.3328000605106354,
                  "Y": 0.25471168756484985
                },
                {
                  "X": 0.4549534320831299,
                  "Y": 0.254118412733078
                },
                {
                  "X": 0.45496881008148193,
                  "Y": 0.2668972313404083
                },
                {
                  "X": 0.3328128457069397,
                  "Y": 0.2675061821937561
                }
              ]
            },
            "Confidence": 99.61408233642578
          },
          "PageNumber": 1
        },
        {
          "Type": {
            "Text": "VENDOR_PHONE",
            "Confidence": 95.30352020263672
          },
          "LabelDetection": {
            "Text": "H/P:",
            "Geometry": {
              "BoundingBox": {
                "Width": 0.02726796269416809,
                "Height": 0.011856239289045334,
                "Left": 0.33814945816993713,
                "Top": 0.30438604950904846
              },
              "Polygon": [
                {
                  "X": 0.33814945816993713,
                  "Y": 0.3045320212841034
                },
                {
                  "X": 0.3654050827026367,
                  "Y": 0.30438604950904846
                },
                {
                  "X": 0.3654174208641052,
                  "Y": 0.3160930871963501
                },
                {
                  "X": 0.33816125988960266,
                  "Y": 0.3162422776222229
                }
              ]
            },
            "Confidence": 95.29993438720703
          },
          "ValueDetection": {
            "Text": "019-7521215",
            "Geometry": {
              "BoundingBox": {
                "Width": 0.08035819232463837,
                "Height": 0.01229029055684805,
                "Left": 0.3731188178062439,
                "Top": 0.3047110140323639
              },
              "Polygon": [
                {
                  "X": 0.3731188178062439,
                  "Y": 0.30514198541641235
                },
                {
                  "X": 0.4534628093242645,
                  "Y": 0.3047110140323639
                },
                {
                  "X": 0.45347699522972107,
                  "Y": 0.3165607750415802
                },
                {
                  "X": 0.3731314539909363,
                  "Y": 0.3170013129711151
                }
              ]
            },
            "Confidence": 95.30040740966797
          },
          "PageNumber": 1
        },
        {
          "Type": {
            "Text": "VENDOR_PHONE",
            "Confidence": 72.57160949707031
          },
          "ValueDetection": {
            "Text": "016-7867868",
            "Geometry": {
              "BoundingBox": {
                "Width": 0.07978501915931702,
                "Height": 0.012022272683680058,
                "Left": 0.37312230467796326,
                "Top": 0.317442923784256
              },
              "Polygon": [
                {
                  "X": 0.37312230467796326,
                  "Y": 0.3178810179233551
                },
                {
                  "X": 0.45289346575737,
                  "Y": 0.317442923784256
                },
                {
                  "X": 0.4529073238372803,
                  "Y": 0.3290178179740906
                },
                {
                  "X": 0.37313464283943176,
                  "Y": 0.32946521043777466
                }
              ]
            },
            "Confidence": 72.57007598876953
          },
          "PageNumber": 1
        }
      ],
      "LineItemGroups": [
        {
          "LineItemGroupIndex": 1,
          "LineItems": [
            {
              "LineItemExpenseFields": [
                {
                  "Type": {
                    "Text": "ITEM",
                    "Confidence": 99.99979400634766
                  },
                  "ValueDetection": {
                    "Text": "DPT.05",
                    "Geometry": {
                      "BoundingBox": {
                        "Width": 0.05702479928731918,
                        "Height": 0.01277437899261713,
                        "Left": 0.3079700469970703,
                        "Top": 0.3782864212989807
                      },
                      "Polygon": [
                        {
                          "X": 0.3079700469970703,
                          "Y": 0.3786340057849884
                        },
                        {
                          "X": 0.3649817705154419,
                          "Y": 0.3782864212989807
                        },
                        {
                          "X": 0.3649948239326477,
                          "Y": 0.3907061219215393
                        },
                        {
                          "X": 0.307981938123703,
                          "Y": 0.39106079936027527
                        }
                      ]
                    },
                    "Confidence": 97.42048645019531
                  },
                  "PageNumber": 1
                },
                {
                  "Type": {
                    "Text": "PRICE",
                    "Confidence": 100.0
                  },
                  "ValueDetection": {
                    "Text": "RM 149.00",
                    "Geometry": {
                      "BoundingBox": {
                        "Width": 0.07313407212495804,
                        "Height": 0.01254638284444809,
                        "Left": 0.39189404249191284,
                        "Top": 0.3796924352645874
                      },
                      "Polygon": [
                        {
                          "X": 0.39189404249191284,
                          "Y": 0.38013970851898193
                        },
                        {
                          "X": 0.46501338481903076,
                          "Y": 0.3796924352645874
                        },
                        {
                          "X": 0.4650281071662903,
                          "Y": 0.39178267121315
                        },
                        {
                          "X": 0.39190730452537537,
                          "Y": 0.3922388255596161
                        }
                      ]
                    },
                    "Confidence": 99.99199676513672
                  },
                  "PageNumber": 1
                },
                {
                  "Type": {
                    "Text": "EXPENSE_ROW",
                    "Confidence": 99.99974822998047
                  },
                  "ValueDetection": {
                    "Text": "DPT.05 RM 149.00",
                    "Geometry": {
                      "BoundingBox": {
                        "Width": 0.15705807507038116,
                        "Height": 0.015085799619555473,
                        "Left": 0.3079700469970703,
                        "Top": 0.3776765763759613
                      },
                      "Polygon": [
                        {
                          "X": 0.3079700469970703,
                          "Y": 0.3786340057849884
                        },
                        {
                          "X": 0.46501094102859497,
                          "Y": 0.3776765763759613
                        },
                        {
                          "X": 0.4650281071662903,
                          "Y": 0.39178267121315
                        },
                        {
                          "X": 0.3079835772514343,
                          "Y": 0.39276236295700073
                        }
                      ]
                    },
                    "Confidence": 99.12718963623047
                  },
                  "PageNumber": 1
                }
              ]
            },
            {
              "LineItemExpenseFields": [
                {
                  "Type": {
                    "Text": "ITEM",
                    "Confidence": 99.99949645996094
                  },
                  "ValueDetection": {
                    "Text": "DPT.04",
                    "Geometry": {
                      "BoundingBox": {
                        "Width": 0.05842633545398712,
                        "Height": 0.01244086679071188,
                        "Left": 0.3064744770526886,
                        "Top": 0.3914036452770233
                      },
                      "Polygon": [
                        {
                          "X": 0.3064744770526886,
                          "Y": 0.3917674720287323
                        },
                        {
                          "X": 0.36488813161849976,
                          "Y": 0.3914036452770233
                        },
                        {
                          "X": 0.3649008274078369,
                          "Y": 0.4034736156463623
                        },
                        {
                          "X": 0.30648601055145264,
                          "Y": 0.4038445055484772
                        }
                      ]
                    },
                    "Confidence": 98.92448425292969
                  },
                  "PageNumber": 1
                },
                {
                  "Type": {
                    "Text": "PRICE",
                    "Confidence": 99.99978637695312
                  },
                  "ValueDetection": {
                    "Text": "RN 21.00",
                    "Geometry": {
                      "BoundingBox": {
                        "Width": 0.06594734638929367,
                        "Height": 0.01275076624006033,
                        "Left": 0.39893636107444763,
                        "Top": 0.39178889989852905
                      },
                      "Polygon": [
                        {
                          "X": 0.39893636107444763,
                          "Y": 0.392200231552124
                        },
                        {
                          "X": 0.4648686945438385,
                          "Y": 0.39178889989852905
                        },
                        {
                          "X": 0.4648837149143219,
                          "Y": 0.40412020683288574
                        },
                        {
                          "X": 0.3989500403404236,
                          "Y": 0.40453967452049255
                        }
                      ]
                    },
                    "Confidence": 99.98793029785156
                  },
                  "PageNumber": 1
                },
                {
                  "Type": {
                    "Text": "EXPENSE_ROW",
                    "Confidence": 99.99995422363281
                  },
                  "ValueDetection": {
                    "Text": "DPT.04 RN 21.00",
                    "Geometry": {
                      "BoundingBox": {
                        "Width": 0.1584092229604721,
                        "Height": 0.014346987940371037,
                        "Left": 0.3064744770526886,
                        "Top": 0.3907809555530548
                      },
                      "Polygon": [
                        {
                          "X": 0.3064744770526886,
                          "Y": 0.3917674720287323
                        },
                        {
                          "X": 0.4648674726486206,
                          "Y": 0.3907809555530548
                        },
                        {
                          "X": 0.4648837149143219,
                          "Y": 0.40412020683288574
                        },
                        {
                          "X": 0.30648723244667053,
                          "Y": 0.40512794256210327
                        }
                      ]
                    },
                    "Confidence": 99.6324462890625
                  },
                  "PageNumber": 1
                }
              ]
            }
          ]
        }
      ],
      "Blocks": [
        {
          "BlockType": "PAGE",
          "Geometry": {
            "BoundingBox": {
              "Width": 1.0,
              "Height": 1.0,
              "Left": 0.0,
              "Top": 0.0
            },
            "Polygon": [
              {
                "X": 0.0,
                "Y": 1.025743813443114e-06
              },
              {
                "X": 1.0,
                "Y": 0.0
              },
              {
                "X": 1.0,
                "Y": 1.0
              },
              {
                "X": 5.865268121851841e-06,
                "Y": 1.0
              }
            ]
          },
          "Id": "a513ac69-a40d-4498-b334-e5b2881cdf1b",
          "Relationships": [
            {
              "Type": "CHILD",
              "Ids": [
                "a22ff2d3-47d2-4952-818b-fe5f3f08b91d",
                "bf9bfb7f-1846-4b3d-a64f-90fbfa66c6b8",
                "ac92f9ab-143e-4447-9d7f-9a4067d8e2fe",
                "5e948f0e-8f1a-4e4b-9db2-ac491fd19188",
                "c223ede1-93b6-4f1e-8f07-a53dd39bc747",
                "7491db2d-893d-4675-aa85-899e3638129f",
                "56d39949-caee-485d-bcd7-4356e48b8c66",
                "9f044c89-7529-4a22-bcc7-ae516b0f67cc",
                "f15300ba-1e06-4fd1-ab3d-6b1a3cfb4488",
                "c6bde4d3-5a3f-4405-b93c-787894933b99",
                "384cb13a-1434-441b-ad85-04495c145c9f",
                "8146a82e-9c16-49c2-8a4d-188663a9e00a",
                "97601b2a-c15d-4d52-af6b-d17340db3250",
                "bf5781f3-7f89-48de-8aeb-0e1e4645f31d",
                "b5605397-7781-4cf9-bcb3-fca81588eb1f",
                "440e1d00-bd0e-4955-b786-4f954b27fae8",
                "064e62bc-b965-4ee6-94fb-7084c001ec5c"
              ]
            }
          ]
        },
        {
          "BlockType": "LINE",
          "Confidence": 24.735065460205078,
          "Text": "403076",
          "Geometry": {
            "BoundingBox": {
              "Width": 0.056709904223680496,
              "Height": 0.016057780012488365,
              "Left": 0.42359012365341187,
              "Top": 0.2436210662126541
            },
            "Polygon": [
              {
                "X": 0.42359012365341187,
                "Y": 0.24389049410820007
              },
              {
                "X": 0.48028039932250977,
                "Y": 0.2436210662126541
              },
              {
                "X": 0.48030003905296326,
                "Y": 0.2594004273414612
              },
              {
                "X": 0.42360827326774597,
                "Y": 0.25967884063720703
              }
            ]
          },
          "Id": "a22ff2d3-47d2-4952-818b-fe5f3f08b91d",
          "Relationships": [
            {
              "Type": "CHILD",
              "Ids": [
                "b8275993-734b-42f0-b6c9-c567388c7d5e"
              ]
            }
          ]
        },
        {
          "BlockType": "LINE",
          "Confidence": 99.4511489868164,
          "Text": "RESTAURANT SIN DU",
          "Geometry": {
            "BoundingBox": {
              "Width": 0.12139817327260971,
              "Height": 0.012857449240982533,
              "Left": 0.3335706293582916,
              "Top": 0.25464487075805664
            },
            "Polygon": [
              {
                "X": 0.3335706293582916,
                "Y": 0.25523507595062256
              },
              {
                "X": 0.4549540877342224,
                "Y": 0.25464487075805664
              },
              {
                "X": 0.45496881008148193,
                "Y": 0.2668972313404083
              },
              {
                "X": 0.33358290791511536,
                "Y": 0.2675023376941681
              }
            ]
          },
          "Id": "bf9bfb7f-1846-4b3d-a64f-90fbfa66c6b8",
          "Relationships": [
            {
              "Type": "CHILD",
              "Ids": [
                "734054cd-f9bd-46e3-bd4d-90fabd6a8781",
                "8228cf47-de4f-4763-bc48-2947d69a4c13",
                "bb27f265-a823-4e36-9508-8a5051c91d41"
              ]
            }
          ]
        },
        {
          "BlockType": "LINE",
          "Confidence": 94.9442367553711,
          "Text": "K3-113, JL IBRAHIM SULTAN",
          "Geometry": {
            "BoundingBox": {
              "Width": 0.1712476760149002,
              "Height": 0.014480983838438988,
              "Left": 0.31156885623931885,
              "Top": 0.2662058174610138
            },
            "Polygon": [
              {
                "X": 0.31156885623931885,
                "Y": 0.26705846190452576
              },
              {
                "X": 0.48279955983161926,
                "Y": 0.2662058174610138
              },
              {
                "X": 0.48281654715538025,
                "Y": 0.27981075644493103
              },
              {
                "X": 0.3115819990634918,
                "Y": 0.28068679571151733
              }
            ]
          },
          "Id": "ac92f9ab-143e-4447-9d7f-9a4067d8e2fe",
          "Relationships": [
            {
              "Type": "CHILD",
              "Ids": [
                "0bd3b931-6e19-4c12-9f58-dc0bafd00c75",
                "612d7da0-7c90-488d-a18d-ccd863ac0b06",
                "20ea218e-f18f-44f4-89db-85824222c8f3",
                "2507c058-028e-4a33-9961-8b3d930c5601"
              ]
            }
          ]
        },
        {
          "BlockType": "LINE",
          "Confidence": 99.6025390625,
          "Text": "80300 JOHOR BAHRU",
          "Geometry": {
            "BoundingBox": {
              "Width": 0.12192762643098831,
              "Height": 0.012723852880299091,
              "Left": 0.3393285572528839,
              "Top": 0.2797423005104065
            },
            "Polygon": [
              {
                "X": 0.3393285572528839,
                "Y": 0.28036579489707947
              },
              {
                "X": 0.46124154329299927,
                "Y": 0.2797423005104065
              },
              {
                "X": 0.4612561762332916,
                "Y": 0.29182788729667664
              },
              {
                "X": 0.33934077620506287,
                "Y": 0.2924661636352539
              }
            ]
          },
          "Id": "5e948f0e-8f1a-4e4b-9db2-ac491fd19188",
          "Relationships": [
            {
              "Type": "CHILD",
              "Ids": [
                "7df0f3e1-367e-40b3-b567-4dac2951ecaf",
                "2432b1b9-49d5-47dd-bc52-0ef86f51aabc",
                "c67dd574-df9d-4866-83a5-7f8ef2d3accd"
              ]
            }
          ]
        },
        {
          "BlockType": "LINE",
          "Confidence": 99.60381317138672,
          "Text": "JOHOR",
          "Geometry": {
            "BoundingBox": {
              "Width": 0.03639884293079376,
              "Height": 0.011262081563472748,
              "Left": 0.3817267119884491,
              "Top": 0.29285845160484314
            },
            "Polygon": [
              {
                "X": 0.3817267119884491,
                "Y": 0.29304924607276917
              },
              {
                "X": 0.41811293363571167,
                "Y": 0.29285845160484314
              },
              {
                "X": 0.41812554001808167,
                "Y": 0.3039257228374481
              },
              {
                "X": 0.38173866271972656,
                "Y": 0.3041205406188965
              }
            ]
          },
          "Id": "c223ede1-93b6-4f1e-8f07-a53dd39bc747",
          "Relationships": [
            {
              "Type": "CHILD",
              "Ids": [
                "6bc92db9-699d-4a4d-91c4-c36730935baf"
              ]
            }
          ]
        },
        {
          "BlockType": "LINE",
          "Confidence": 99.5374755859375,
          "Text": "H/P: 019-7521215",
          "Geometry": {
            "BoundingBox": {
              "Width": 0.11532755941152573,
              "Height": 0.013278651051223278,
              "Left": 0.33814945816993713,
              "Top": 0.3039143979549408
            },
            "Polygon": [
              {
                "X": 0.33814945816993713,
                "Y": 0.3045320212841034
              },
              {
                "X": 0.4534618556499481,
                "Y": 0.3039143979549408
              },
              {
                "X": 0.45347699522972107,
                "Y": 0.3165607750415802
              },
              {
                "X": 0.33816221356391907,
                "Y": 0.31719303131103516
              }
            ]
          },
          "Id": "7491db2d-893d-4675-aa85-899e3638129f",
          "Relationships": [
            {
              "Type": "CHILD",
              "Ids": [
                "9250c8a1-8261-4227-935e-f4ce14168423",
                "f1f501c3-fc20-47c9-b40d-2ed73fd28e9f"
              ]
            }
          ]
        },
        {
          "BlockType": "LINE",
          "Confidence": 99.53089141845703,
          "Text": "016-7867868",
          "Geometry": {
            "BoundingBox": {
              "Width": 0.07978501915931702,
              "Height": 0.012022272683680058,
              "Left": 0.37312230467796326,
              "Top": 0.317442923784256
            },
            "Polygon": [
              {
                "X": 0.37312230467796326,
                "Y": 0.3178810179233551
              },
              {
                "X": 0.45289346575737,
                "Y": 0.317442923784256
              },
              {
                "X": 0.4529073238372803,
                "Y": 0.3290178179740906
              },
              {
                "X": 0.37313464283943176,
                "Y": 0.32946521043777466
              }
            ]
          },
          "Id": "56d39949-caee-485d-bcd7-4356e48b8c66",
          "Relationships": [
            {
              "Type": "CHILD",
              "Ids": [
                "d95c056a-1038-4a24-a0d5-0971ae269f96"
              ]
            }
          ]
        },
        {
          "BlockType": "LINE",
          "Confidence": 98.5173568725586,
          "Text": "09/03/2018 21:28",
          "Geometry": {
            "BoundingBox": {
              "Width": 0.1149030551314354,
              "Height": 0.012460163794457912,
              "Left": 0.30856069922447205,
              "Top": 0.34206268191337585
            },
            "Polygon": [
              {
                "X": 0.30856069922447205,
                "Y": 0.3427218198776245
              },
              {
                "X": 0.423450231552124,
                "Y": 0.34206268191337585
              },
              {
                "X": 0.42346376180648804,
                "Y": 0.3538500964641571
              },
              {
                "X": 0.30857202410697937,
                "Y": 0.35452282428741455
              }
            ]
          },
          "Id": "9f044c89-7529-4a22-bcc7-ae516b0f67cc",
          "Relationships": [
            {
              "Type": "CHILD",
              "Ids": [
                "38d1296d-42a3-4056-94c4-84d5afbe0bf4",
                "6b515898-102c-4141-8163-fc913e5975d1"
              ]
            }
          ]
        },
        {
          "BlockType": "LINE",
          "Confidence": 99.86437225341797,
          "Text": "0001",
          "Geometry": {
            "BoundingBox": {
              "Width": 0.028166022151708603,
              "Height": 0.01122529897838831,
              "Left": 0.4505355656147003,
              "Top": 0.34335294365882874
            },
            "Polygon": [
              {
                "X": 0.4505355656147003,
                "Y": 0.34351491928100586
              },
              {
                "X": 0.4786878526210785,
                "Y": 0.34335294365882874
              },
              {
                "X": 0.4787015914916992,
                "Y": 0.35441315174102783
              },
              {
                "X": 0.45054876804351807,
                "Y": 0.35457825660705566
              }
            ]
          },
          "Id": "f15300ba-1e06-4fd1-ab3d-6b1a3cfb4488",
          "Relationships": [
            {
              "Type": "CHILD",
              "Ids": [
                "a4f23113-3f7e-475a-bbeb-95d599c92ca7"
              ]
            }
          ]
        },
        {
          "BlockType": "LINE",
          "Confidence": 98.16729736328125,
          "Text": "000000#7259 CASHIER01",
          "Geometry": {
            "BoundingBox": {
              "Width": 0.14873923361301422,
              "Height": 0.012961108237504959,
              "Left": 0.30836567282676697,
              "Top": 0.3542484641075134
            },
            "Polygon": [
              {
                "X": 0.30836567282676697,
                "Y": 0.3551201820373535
              },
              {
                "X": 0.4570903480052948,
                "Y": 0.3542484641075134
              },
              {
                "X": 0.45710489153862,
                "Y": 0.36631980538368225
              },
              {
                "X": 0.3083772659301758,
                "Y": 0.3672095537185669
              }
            ]
          },
          "Id": "c6bde4d3-5a3f-4405-b93c-787894933b99",
          "Relationships": [
            {
              "Type": "CHILD",
              "Ids": [
                "1571512f-4bed-45e3-a265-feaf55be995b",
                "bc8a7d02-f7a1-45bf-b37e-4ca138d0e68d"
              ]
            }
          ]
        },
        {
          "BlockType": "LINE",
          "Confidence": 76.25100708007812,
          "Text": "DPT.05",
          "Geometry": {
            "BoundingBox": {
              "Width": 0.05458701774477959,
              "Height": 0.011932546272873878,
              "Left": 0.30945777893066406,
              "Top": 0.37911900877952576
            },
            "Polygon": [
              {
                "X": 0.30945777893066406,
                "Y": 0.3794521987438202
              },
              {
                "X": 0.3640326261520386,
                "Y": 0.37911900877952576
              },
              {
                "X": 0.36404481530189514,
                "Y": 0.39071202278137207
              },
              {
                "X": 0.30946892499923706,
                "Y": 0.3910515606403351
              }
            ]
          },
          "Id": "384cb13a-1434-441b-ad85-04495c145c9f",
          "Relationships": [
            {
              "Type": "CHILD",
              "Ids": [
                "51272637-7129-42f4-8c6d-2f0bab120467"
              ]
            }
          ]
        },
        {
          "BlockType": "LINE",
          "Confidence": 90.25658416748047,
          "Text": "RM 149.00",
          "Geometry": {
            "BoundingBox": {
              "Width": 0.07233425229787827,
              "Height": 0.012411809526383877,
              "Left": 0.3926938474178314,
              "Top": 0.3798220157623291
            },
            "Polygon": [
              {
                "X": 0.3926938474178314,
                "Y": 0.3802644908428192
              },
              {
                "X": 0.4650135338306427,
                "Y": 0.3798220157623291
              },
              {
                "X": 0.4650281071662903,
                "Y": 0.39178267121315
              },
              {
                "X": 0.3927069902420044,
                "Y": 0.39223381876945496
              }
            ]
          },
          "Id": "8146a82e-9c16-49c2-8a4d-188663a9e00a",
          "Relationships": [
            {
              "Type": "CHILD",
              "Ids": [
                "9d4c3d67-115e-460b-89ba-67aa76b64a76",
                "38aa4dd4-9aed-4080-a74b-8584cea6a365"
              ]
            }
          ]
        },
        {
          "BlockType": "LINE",
          "Confidence": 46.079139709472656,
          "Text": "DPT.04",
          "Geometry": {
            "BoundingBox": {
              "Width": 0.05803728848695755,
              "Height": 0.011916667222976685,
              "Left": 0.3068635165691376,
              "Top": 0.3919253647327423
            },
            "Polygon": [
              {
                "X": 0.3068635165691376,
                "Y": 0.39228707551956177
              },
              {
                "X": 0.36488866806030273,
                "Y": 0.3919253647327423
              },
              {
                "X": 0.3649008274078369,
                "Y": 0.4034736156463623
              },
              {
                "X": 0.3068745732307434,
                "Y": 0.403842031955719
              }
            ]
          },
          "Id": "97601b2a-c15d-4d52-af6b-d17340db3250",
          "Relationships": [
            {
              "Type": "CHILD",
              "Ids": [
                "1cabf2db-5e93-4b9a-ba37-76d4112c1548"
              ]
            }
          ]
        },
        {
          "BlockType": "LINE",
          "Confidence": 81.64450073242188,
          "Text": "RN 21.00",
          "Geometry": {
            "BoundingBox": {
              "Width": 0.06584272533655167,
              "Height": 0.01224768627434969,
              "Left": 0.39904096722602844,
              "Top": 0.3922913372516632
            },
            "Polygon": [
              {
                "X": 0.39904096722602844,
                "Y": 0.3927023112773895
              },
              {
                "X": 0.46486929059028625,
                "Y": 0.3922913372516632
              },
              {
                "X": 0.4648837149143219,
                "Y": 0.40412020683288574
              },
              {
                "X": 0.3990541100502014,
                "Y": 0.4045390188694
              }
            ]
          },
          "Id": "bf5781f3-7f89-48de-8aeb-0e1e4645f31d",
          "Relationships": [
            {
              "Type": "CHILD",
              "Ids": [
                "78af4862-3f0a-47d8-ae31-427feabcc51b",
                "76d390c2-8af9-4c38-b4b3-8994aa826820"
              ]
            }
          ]
        },
        {
          "BlockType": "LINE",
          "Confidence": 99.9061279296875,
          "Text": "CASH",
          "Geometry": {
            "BoundingBox": {
              "Width": 0.03638587146997452,
              "Height": 0.01082654856145382,
              "Left": 0.30726638436317444,
              "Top": 0.41730374097824097
            },
            "Polygon": [
              {
                "X": 0.30726638436317444,
                "Y": 0.41753968596458435
              },
              {
                "X": 0.3436414897441864,
                "Y": 0.41730374097824097
              },
              {
                "X": 0.34365224838256836,
                "Y": 0.42789047956466675
              },
              {
                "X": 0.30727651715278625,
                "Y": 0.42813029885292053
              }
            ]
          },
          "Id": "b5605397-7781-4cf9-bcb3-fca81588eb1f",
          "Relationships": [
            {
              "Type": "CHILD",
              "Ids": [
                "b86c694a-c78e-46cf-abd7-2e335981c383"
              ]
            }
          ]
        },
        {
          "BlockType": "LINE",
          "Confidence": 99.91385650634766,
          "Text": "RM",
          "Geometry": {
            "BoundingBox": {
              "Width": 0.02926143817603588,
              "Height": 0.01157044805586338,
              "Left": 0.3204685151576996,
              "Top": 0.42958319187164307
            },
            "Polygon": [
              {
                "X": 0.3204685151576996,
                "Y": 0.42977651953697205
              },
              {
                "X": 0.34971827268600464,
                "Y": 0.42958319187164307
              },
              {
                "X": 0.3497299551963806,
                "Y": 0.4409569501876831
              },
              {
                "X": 0.3204796314239502,
                "Y": 0.4411536157131195
              }
            ]
          },
          "Id": "440e1d00-bd0e-4955-b786-4f954b27fae8",
          "Relationships": [
            {
              "Type": "CHILD",
              "Ids": [
                "16cc15d1-6b8d-48a4-90fe-c50ccd91af6e"
              ]
            }
          ]
        },
        {
          "BlockType": "LINE",
          "Confidence": 96.82833862304688,
          "Text": "170.00",
          "Geometry": {
            "BoundingBox": {
              "Width": 0.08422455936670303,
              "Height": 0.01301357802003622,
              "Left": 0.37904903292655945,
              "Top": 0.4292886257171631
            },
            "Polygon": [
              {
                "X": 0.37904903292655945,
                "Y": 0.4298456311225891
              },
              {
                "X": 0.4632584750652313,
                "Y": 0.4292886257171631
              },
              {
                "X": 0.4632735848426819,
                "Y": 0.4417346715927124
              },
              {
                "X": 0.3790624141693115,
                "Y": 0.4423021972179413
              }
            ]
          },
          "Id": "064e62bc-b965-4ee6-94fb-7084c001ec5c",
          "Relationships": [
            {
              "Type": "CHILD",
              "Ids": [
                "e3b7ba49-0b65-4257-a614-874fa9b38a40"
              ]
            }
          ]
        },
        {
          "BlockType": "WORD",
          "Confidence": 24.735065460205078,
          "Text": "403076",
          "TextType": "PRINTED",
          "Geometry": {
            "BoundingBox": {
              "Width": 0.056709904223680496,
              "Height": 0.016057780012488365,
              "Left": 0.42359012365341187,
              "Top": 0.2436210662126541
            },
            "Polygon": [
              {
                "X": 0.42359012365341187,
                "Y": 0.24389049410820007
              },
              {
                "X": 0.48028039932250977,
                "Y": 0.2436210662126541
              },
              {
                "X": 0.48030003905296326,
                "Y": 0.2594004273414612
              },
              {
                "X": 0.42360827326774597,
                "Y": 0.25967884063720703
              }
            ]
          },
          "Id": "b8275993-734b-42f0-b6c9-c567388c7d5e",
          "Page": 1
        },
        {
          "BlockType": "WORD",
          "Confidence": 99.7113265991211,
          "Text": "RESTAURANT",
          "TextType": "PRINTED",
          "Geometry": {
            "BoundingBox": {
              "Width": 0.06979504972696304,
              "Height": 0.011324374936521053,
              "Left": 0.3335706293582916,
              "Top": 0.25489577651023865
            },
            "Polygon": [
              {
                "X": 0.3335706293582916,
                "Y": 0.25523507595062256
              },
              {
                "X": 0.40335342288017273,
                "Y": 0.25489577651023865
              },
              {
                "X": 0.4033656716346741,
                "Y": 0.26587316393852234
              },
              {
                "X": 0.3335816264152527,
                "Y": 0.2662201523780823
              }
            ]
          },
          "Id": "734054cd-f9bd-46e3-bd4d-90fabd6a8781",
          "Page": 1
        },
        {
          "BlockType": "WORD",
          "Confidence": 99.91023254394531,
          "Text": "SIN",
          "TextType": "PRINTED",
          "Geometry": {
            "BoundingBox": {
              "Width": 0.02337118424475193,
              "Height": 0.01187772024422884,
              "Left": 0.4100368022918701,
              "Top": 0.25498831272125244
            },
            "Polygon": [
              {
                "X": 0.4100368022918701,
                "Y": 0.25510191917419434
              },
              {
                "X": 0.43339428305625916,
                "Y": 0.25498831272125244
              },
              {
                "X": 0.4334079921245575,
                "Y": 0.26674965023994446
              },
              {
                "X": 0.41005006432533264,
                "Y": 0.2668660283088684
              }
            ]
          },
          "Id": "8228cf47-de4f-4763-bc48-2947d69a4c13",
          "Page": 1
        },
        {
          "BlockType": "WORD",
          "Confidence": 98.73187255859375,
          "Text": "DU",
          "TextType": "PRINTED",
          "Geometry": {
            "BoundingBox": {
              "Width": 0.016052817925810814,
              "Height": 0.011505227535963058,
              "Left": 0.4389159679412842,
              "Top": 0.25547194480895996
            },
            "Polygon": [
              {
                "X": 0.4389159679412842,
                "Y": 0.2555500566959381
              },
              {
                "X": 0.4549550712108612,
                "Y": 0.25547194480895996
              },
              {
                "X": 0.45496881008148193,
                "Y": 0.2668972313404083
              },
              {
                "X": 0.43892940878868103,
                "Y": 0.2669771909713745
              }
            ]
          },
          "Id": "bb27f265-a823-4e36-9508-8a5051c91d41",
          "Page": 1
        },
        {
          "BlockType": "WORD",
          "Confidence": 81.02337646484375,
          "Text": "K3-113,",
          "TextType": "PRINTED",
          "Geometry": {
            "BoundingBox": {
              "Width": 0.047223880887031555,
              "Height": 0.011804593726992607,
              "Left": 0.31156885623931885,
              "Top": 0.26682335138320923
            },
            "Polygon": [
              {
                "X": 0.31156885623931885,
                "Y": 0.26705846190452576
              },
              {
                "X": 0.3587806820869446,
                "Y": 0.26682335138320923
              },
              {
                "X": 0.3587927222251892,
                "Y": 0.2783873975276947
              },
              {
                "X": 0.31158000230789185,
                "Y": 0.2786279618740082
              }
            ]
          },
          "Id": "0bd3b931-6e19-4c12-9f58-dc0bafd00c75",
          "Page": 1
        },
        {
          "BlockType": "WORD",
          "Confidence": 99.39694213867188,
          "Text": "JL",
          "TextType": "PRINTED",
          "Geometry": {
            "BoundingBox": {
              "Width": 0.01332889124751091,
              "Height": 0.011754252947866917,
              "Left": 0.361635684967041,
              "Top": 0.26724064350128174
            },
            "Polygon": [
              {
                "X": 0.361635684967041,
                "Y": 0.26730701327323914
              },
              {
                "X": 0.3749520778656006,
                "Y": 0.26724064350128174
              },
              {
                "X": 0.37496456503868103,
                "Y": 0.27892693877220154
              },
              {
                "X": 0.36164790391921997,
                "Y": 0.2789948880672455
              }
            ]
          },
          "Id": "612d7da0-7c90-488d-a18d-ccd863ac0b06",
          "Page": 1
        },
        {
          "BlockType": "WORD",
          "Confidence": 99.654296875,
          "Text": "IBRAHIM",
          "TextType": "PRINTED",
          "Geometry": {
            "BoundingBox": {
              "Width": 0.05067453905940056,
              "Height": 0.012340696528553963,
              "Left": 0.3823840916156769,
              "Top": 0.26733654737472534
            },
            "Polygon": [
              {
                "X": 0.3823840916156769,
                "Y": 0.2675892412662506
              },
              {
                "X": 0.43304455280303955,
                "Y": 0.26733654737472534
              },
              {
                "X": 0.43305861949920654,
                "Y": 0.27941837906837463
              },
              {
                "X": 0.3823971748352051,
                "Y": 0.27967724204063416
              }
            ]
          },
          "Id": "20ea218e-f18f-44f4-89db-85824222c8f3",
          "Page": 1
        },
        {
          "BlockType": "WORD",
          "Confidence": 99.70233917236328,
          "Text": "SULTAN",
          "TextType": "PRINTED",
          "Geometry": {
            "BoundingBox": {
              "Width": 0.04432051628828049,
              "Height": 0.012330202385783195,
              "Left": 0.43849602341651917,
              "Top": 0.2677072286605835
            },
            "Polygon": [
              {
                "X": 0.43849602341651917,
                "Y": 0.26792851090431213
              },
              {
                "X": 0.4828014373779297,
                "Y": 0.2677072286605835
              },
              {
                "X": 0.48281654715538025,
                "Y": 0.27981075644493103
              },
              {
                "X": 0.4385102391242981,
                "Y": 0.28003743290901184
              }
            ]
          },
          "Id": "2507c058-028e-4a33-9961-8b3d930c5601",
          "Page": 1
        },
        {
          "BlockType": "WORD",
          "Confidence": 99.75871276855469,
          "Text": "80300",
          "TextType": "PRINTED",
          "Geometry": {
            "BoundingBox": {
              "Width": 0.03630039095878601,
              "Height": 0.010937714017927647,
              "Left": 0.3393285572528839,
              "Top": 0.2801802158355713
            },
            "Polygon": [
              {
                "X": 0.3393285572528839,
                "Y": 0.28036579489707947
              },
              {
                "X": 0.37561744451522827,
                "Y": 0.2801802158355713
              },
              {
                "X": 0.3756289482116699,
                "Y": 0.2909284234046936
              },
              {
                "X": 0.33933940529823303,
                "Y": 0.29111790657043457
              }
            ]
          },
          "Id": "7df0f3e1-367e-40b3-b567-4dac2951ecaf",
          "Page": 1
        },
        {
          "BlockType": "WORD",
          "Confidence": 99.3418197631836,
          "Text": "JOHOR",
          "TextType": "PRINTED",
          "Geometry": {
            "BoundingBox": {
              "Width": 0.03586295619606972,
              "Height": 0.011644680984318256,
              "Left": 0.3825303018093109,
              "Top": 0.2803196907043457
            },
            "Polygon": [
              {
                "X": 0.3825303018093109,
                "Y": 0.28050315380096436
              },
              {
                "X": 0.4183802008628845,
                "Y": 0.2803196907043457
              },
              {
                "X": 0.41839325428009033,
                "Y": 0.29177677631378174
              },
              {
                "X": 0.3825426995754242,
                "Y": 0.2919643819332123
              }
            ]
          },
          "Id": "2432b1b9-49d5-47dd-bc52-0ef86f51aabc",
          "Page": 1
        },
        {
          "BlockType": "WORD",
          "Confidence": 99.70708465576172,
          "Text": "BAHRU",
          "TextType": "PRINTED",
          "Geometry": {
            "BoundingBox": {
              "Width": 0.036854539066553116,
              "Height": 0.01169910654425621,
              "Left": 0.4244016408920288,
              "Top": 0.2803216576576233
            },
            "Polygon": [
              {
                "X": 0.4244016408920288,
                "Y": 0.280510276556015
              },
              {
                "X": 0.4612422585487366,
                "Y": 0.2803216576576233
              },
              {
                "X": 0.4612561762332916,
                "Y": 0.29182788729667664
              },
              {
                "X": 0.42441490292549133,
                "Y": 0.2920207679271698
              }
            ]
          },
          "Id": "c67dd574-df9d-4866-83a5-7f8ef2d3accd",
          "Page": 1
        },
        {
          "BlockType": "WORD",
          "Confidence": 99.60381317138672,
          "Text": "JOHOR",
          "TextType": "PRINTED",
          "Geometry": {
            "BoundingBox": {
              "Width": 0.03639884293079376,
              "Height": 0.011262081563472748,
              "Left": 0.3817267119884491,
              "Top": 0.29285845160484314
            },
            "Polygon": [
              {
                "X": 0.3817267119884491,
                "Y": 0.29304924607276917
              },
              {
                "X": 0.41811293363571167,
                "Y": 0.29285845160484314
              },
              {
                "X": 0.41812554001808167,
                "Y": 0.3039257228374481
              },
              {
                "X": 0.38173866271972656,
                "Y": 0.3041205406188965
              }
            ]
          },
          "Id": "6bc92db9-699d-4a4d-91c4-c36730935baf",
          "Page": 1
        },
        {
          "BlockType": "WORD",
          "Confidence": 99.24530029296875,
          "Text": "H/P:",
          "TextType": "PRINTED",
          "Geometry": {
            "BoundingBox": {
              "Width": 0.02726796269416809,
              "Height": 0.011856239289045334,
              "Left": 0.33814945816993713,
              "Top": 0.30438604950904846
            },
            "Polygon": [
              {
                "X": 0.33814945816993713,
                "Y": 0.3045320212841034
              },
              {
                "X": 0.3654050827026367,
                "Y": 0.30438604950904846
              },
              {
                "X": 0.3654174208641052,
                "Y": 0.3160930871963501
              },
              {
                "X": 0.33816125988960266,
                "Y": 0.3162422776222229
              }
            ]
          },
          "Id": "9250c8a1-8261-4227-935e-f4ce14168423",
          "Page": 1
        },
        {
          "BlockType": "WORD",
          "Confidence": 99.82964324951172,
          "Text": "019-7521215",
          "TextType": "PRINTED",
          "Geometry": {
            "BoundingBox": {
              "Width": 0.08035819232463837,
              "Height": 0.01229029055684805,
              "Left": 0.3731188178062439,
              "Top": 0.3047110140323639
            },
            "Polygon": [
              {
                "X": 0.3731188178062439,
                "Y": 0.30514198541641235
              },
              {
                "X": 0.4534628093242645,
                "Y": 0.3047110140323639
              },
              {
                "X": 0.45347699522972107,
                "Y": 0.3165607750415802
              },
              {
                "X": 0.3731314539909363,
                "Y": 0.3170013129711151
              }
            ]
          },
          "Id": "f1f501c3-fc20-47c9-b40d-2ed73fd28e9f",
          "Page": 1
        },
        {
          "BlockType": "WORD",
          "Confidence": 99.53089141845703,
          "Text": "016-7867868",
          "TextType": "PRINTED",
          "Geometry": {
            "BoundingBox": {
              "Width": 0.07978501915931702,
              "Height": 0.012022272683680058,
              "Left": 0.37312230467796326,
              "Top": 0.317442923784256
            },
            "Polygon": [
              {
                "X": 0.37312230467796326,
                "Y": 0.3178810179233551
              },
              {
                "X": 0.45289346575737,
                "Y": 0.317442923784256
              },
              {
                "X": 0.4529073238372803,
                "Y": 0.3290178179740906
              },
              {
                "X": 0.37313464283943176,
                "Y": 0.32946521043777466
              }
            ]
          },
          "Id": "d95c056a-1038-4a24-a0d5-0971ae269f96",
          "Page": 1
        },
        {
          "BlockType": "WORD",
          "Confidence": 99.91796875,
          "Text": "09/03/2018",
          "TextType": "PRINTED",
          "Geometry": {
            "BoundingBox": {
              "Width": 0.07262688130140305,
              "Height": 0.0116124851629138,
              "Left": 0.30856069922447205,
              "Top": 0.3423052132129669
            },
            "Polygon": [
              {
                "X": 0.30856069922447205,
                "Y": 0.3427218198776245
              },
              {
                "X": 0.38117551803588867,
                "Y": 0.3423052132129669
              },
              {
                "X": 0.3811875879764557,
                "Y": 0.35349294543266296
              },
              {
                "X": 0.308571457862854,
                "Y": 0.3539176881313324
              }
            ]
          },
          "Id": "38d1296d-42a3-4056-94c4-84d5afbe0bf4",
          "Page": 1
        },
        {
          "BlockType": "WORD",
          "Confidence": 97.11675262451172,
          "Text": "21:28",
          "TextType": "PRINTED",
          "Geometry": {
            "BoundingBox": {
              "Width": 0.036697037518024445,
              "Height": 0.011460982263088226,
              "Left": 0.3867667317390442,
              "Top": 0.3426039218902588
            },
            "Polygon": [
              {
                "X": 0.3867667317390442,
                "Y": 0.3428145945072174
              },
              {
                "X": 0.4234508275985718,
                "Y": 0.3426039218902588
              },
              {
                "X": 0.42346376180648804,
                "Y": 0.3538500964641571
              },
              {
                "X": 0.38677898049354553,
                "Y": 0.3540649116039276
              }
            ]
          },
          "Id": "6b515898-102c-4141-8163-fc913e5975d1",
          "Page": 1
        },
        {
          "BlockType": "WORD",
          "Confidence": 99.86437225341797,
          "Text": "0001",
          "TextType": "PRINTED",
          "Geometry": {
            "BoundingBox": {
              "Width": 0.028166022151708603,
              "Height": 0.01122529897838831,
              "Left": 0.4505355656147003,
              "Top": 0.34335294365882874
            },
            "Polygon": [
              {
                "X": 0.4505355656147003,
                "Y": 0.34351491928100586
              },
              {
                "X": 0.4786878526210785,
                "Y": 0.34335294365882874
              },
              {
                "X": 0.4787015914916992,
                "Y": 0.35441315174102783
              },
              {
                "X": 0.45054876804351807,
                "Y": 0.35457825660705566
              }
            ]
          },
          "Id": "a4f23113-3f7e-475a-bbeb-95d599c92ca7",
          "Page": 1
        },
        {
          "BlockType": "WORD",
          "Confidence": 97.55512237548828,
          "Text": "000000#7259",
          "TextType": "PRINTED",
          "Geometry": {
            "BoundingBox": {
              "Width": 0.07946307957172394,
              "Height": 0.01165998075157404,
              "Left": 0.30836567282676697,
              "Top": 0.3546544909477234
            },
            "Polygon": [
              {
                "X": 0.30836567282676697,
                "Y": 0.3551201820373535
              },
              {
                "X": 0.38781654834747314,
                "Y": 0.3546544909477234
              },
              {
                "X": 0.3878287374973297,
                "Y": 0.3658398687839508
              },
              {
                "X": 0.30837640166282654,
                "Y": 0.36631447076797485
              }
            ]
          },
          "Id": "1571512f-4bed-45e3-a265-feaf55be995b",
          "Page": 1
        },
        {
          "BlockType": "WORD",
          "Confidence": 98.77946472167969,
          "Text": "CASHIER01",
          "TextType": "PRINTED",
          "Geometry": {
            "BoundingBox": {
              "Width": 0.06373760104179382,
              "Height": 0.011661754921078682,
              "Left": 0.39336729049682617,
              "Top": 0.3550392985343933
            },
            "Polygon": [
              {
                "X": 0.39336729049682617,
                "Y": 0.3554132878780365
              },
              {
                "X": 0.4570913016796112,
                "Y": 0.3550392985343933
              },
              {
                "X": 0.45710489153862,
                "Y": 0.36631980538368225
              },
              {
                "X": 0.39337971806526184,
                "Y": 0.36670103669166565
              }
            ]
          },
          "Id": "bc8a7d02-f7a1-45bf-b37e-4ca138d0e68d",
          "Page": 1
        },
        {
          "BlockType": "WORD",
          "Confidence": 76.25100708007812,
          "Text": "DPT.05",
          "TextType": "PRINTED",
          "Geometry": {
            "BoundingBox": {
              "Width": 0.05458701774477959,
              "Height": 0.011932546272873878,
              "Left": 0.30945777893066406,
              "Top": 0.37911900877952576
            },
            "Polygon": [
              {
                "X": 0.30945777893066406,
                "Y": 0.3794521987438202
              },
              {
                "X": 0.3640326261520386,
                "Y": 0.37911900877952576
              },
              {
                "X": 0.36404481530189514,
                "Y": 0.39071202278137207
              },
              {
                "X": 0.30946892499923706,
                "Y": 0.3910515606403351
              }
            ]
          },
          "Id": "51272637-7129-42f4-8c6d-2f0bab120467",
          "Page": 1
        },
        {
          "BlockType": "WORD",
          "Confidence": 80.59894561767578,
          "Text": "RM",
          "TextType": "PRINTED",
          "Geometry": {
            "BoundingBox": {
              "Width": 0.015938661992549896,
              "Height": 0.011176428757607937,
              "Left": 0.3926938474178314,
              "Top": 0.38016706705093384
            },
            "Polygon": [
              {
                "X": 0.3926938474178314,
                "Y": 0.3802644908428192
              },
              {
                "X": 0.40862005949020386,
                "Y": 0.38016706705093384
              },
              {
                "X": 0.4086325168609619,
                "Y": 0.3912442624568939
              },
              {
                "X": 0.392706036567688,
                "Y": 0.39134347438812256
              }
            ]
          },
          "Id": "9d4c3d67-115e-460b-89ba-67aa76b64a76",
          "Page": 1
        },
        {
          "BlockType": "WORD",
          "Confidence": 99.91421508789062,
          "Text": "149.00",
          "TextType": "PRINTED",
          "Geometry": {
            "BoundingBox": {
              "Width": 0.043446652591228485,
              "Height": 0.011923919431865215,
              "Left": 0.4215814471244812,
              "Top": 0.38012969493865967
            },
            "Polygon": [
              {
                "X": 0.4215814471244812,
                "Y": 0.3803955614566803
              },
              {
                "X": 0.46501392126083374,
                "Y": 0.38012969493865967
              },
              {
                "X": 0.4650281071662903,
                "Y": 0.39178267121315
              },
              {
                "X": 0.4215948283672333,
                "Y": 0.39205360412597656
              }
            ]
          },
          "Id": "38aa4dd4-9aed-4080-a74b-8584cea6a365",
          "Page": 1
        },
        {
          "BlockType": "WORD",
          "Confidence": 46.079139709472656,
          "Text": "DPT.04",
          "TextType": "PRINTED",
          "Geometry": {
            "BoundingBox": {
              "Width": 0.05803728848695755,
              "Height": 0.011916667222976685,
              "Left": 0.3068635165691376,
              "Top": 0.3919253647327423
            },
            "Polygon": [
              {
                "X": 0.3068635165691376,
                "Y": 0.39228707551956177
              },
              {
                "X": 0.36488866806030273,
                "Y": 0.3919253647327423
              },
              {
                "X": 0.3649008274078369,
                "Y": 0.4034736156463623
              },
              {
                "X": 0.3068745732307434,
                "Y": 0.403842031955719
              }
            ]
          },
          "Id": "1cabf2db-5e93-4b9a-ba37-76d4112c1548",
          "Page": 1
        },
        {
          "BlockType": "WORD",
          "Confidence": 63.3656005859375,
          "Text": "RN",
          "TextType": "PRINTED",
          "Geometry": {
            "BoundingBox": {
              "Width": 0.01595148630440235,
              "Height": 0.011197062209248543,
              "Left": 0.39904096722602844,
              "Top": 0.392602801322937
            },
            "Polygon": [
              {
                "X": 0.39904096722602844,
                "Y": 0.3927023112773895
              },
              {
                "X": 0.41497987508773804,
                "Y": 0.392602801322937
              },
              {
                "X": 0.41499245166778564,
                "Y": 0.403698593378067
              },
              {
                "X": 0.39905327558517456,
                "Y": 0.4037998616695404
              }
            ]
          },
          "Id": "78af4862-3f0a-47d8-ae31-427feabcc51b",
          "Page": 1
        },
        {
          "BlockType": "WORD",
          "Confidence": 99.92339324951172,
          "Text": "21.00",
          "TextType": "PRINTED",
          "Geometry": {
            "BoundingBox": {
              "Width": 0.03732893615961075,
              "Height": 0.011234953068196774,
              "Left": 0.42755475640296936,
              "Top": 0.3931226432323456
            },
            "Polygon": [
              {
                "X": 0.42755475640296936,
                "Y": 0.39335593581199646
              },
              {
                "X": 0.46487030386924744,
                "Y": 0.3931226432323456
              },
              {
                "X": 0.4648837149143219,
                "Y": 0.40412020683288574
              },
              {
                "X": 0.4275674819946289,
                "Y": 0.4043576121330261
              }
            ]
          },
          "Id": "76d390c2-8af9-4c38-b4b3-8994aa826820",
          "Page": 1
        },
        {
          "BlockType": "WORD",
          "Confidence": 99.9061279296875,
          "Text": "CASH",
          "TextType": "PRINTED",
          "Geometry": {
            "BoundingBox": {
              "Width": 0.03638587146997452,
              "Height": 0.01082654856145382,
              "Left": 0.30726638436317444,
              "Top": 0.41730374097824097
            },
            "Polygon": [
              {
                "X": 0.30726638436317444,
                "Y": 0.41753968596458435
              },
              {
                "X": 0.3436414897441864,
                "Y": 0.41730374097824097
              },
              {
                "X": 0.34365224838256836,
                "Y": 0.42789047956466675
              },
              {
                "X": 0.30727651715278625,
                "Y": 0.42813029885292053
              }
            ]
          },
          "Id": "b86c694a-c78e-46cf-abd7-2e335981c383",
          "Page": 1
        },
        {
          "BlockType": "WORD",
          "Confidence": 99.91385650634766,
          "Text": "RM",
          "TextType": "PRINTED",
          "Geometry": {
            "BoundingBox": {
              "Width": 0.02926143817603588,
              "Height": 0.01157044805586338,
              "Left": 0.3204685151576996,
              "Top": 0.42958319187164307
            },
            "Polygon": [
              {
                "X": 0.3204685151576996,
                "Y": 0.42977651953697205
              },
              {
                "X": 0.34971827268600464,
                "Y": 0.42958319187164307
              },
              {
                "X": 0.3497299551963806,
                "Y": 0.4409569501876831
              },
              {
                "X": 0.3204796314239502,
                "Y": 0.4411536157131195
              }
            ]
          },
          "Id": "16cc15d1-6b8d-48a4-90fe-c50ccd91af6e",
          "Page": 1
        },
        {
          "BlockType": "WORD",
          "Confidence": 96.82833862304688,
          "Text": "170.00",
          "TextType": "PRINTED",
          "Geometry": {
            "BoundingBox": {
              "Width": 0.08422455936670303,
              "Height": 0.01301357802003622,
              "Left": 0.37904903292655945,
              "Top": 0.4292886257171631
            },
            "Polygon": [
              {
                "X": 0.37904903292655945,
                "Y": 0.4298456311225891
              },
              {
                "X": 0.4632584750652313,
                "Y": 0.4292886257171631
              },
              {
                "X": 0.4632735848426819,
                "Y": 0.4417346715927124
              },
              {
                "X": 0.3790624141693115,
                "Y": 0.4423021972179413
              }
            ]
          },
          "Id": "e3b7ba49-0b65-4257-a614-874fa9b38a40",
          "Page": 1
        }
      ]
    }
  ],
  "ResponseMetadata": {
    "RequestId": "2c6f62b0-287c-474f-b8d7-df451087d007",
    "HTTPStatusCode": 200,
    "HTTPHeaders": {
      "x-amzn-requestid": "2c6f62b0-287c-474f-b8d7-df451087d007",
      "content-type": "application/x-amz-json-1.1",
      "content-length": "36893",
      "date": "Fri, 25 Apr 2025 16:10:29 GMT"
    },
    "RetryAttempts": 0
  }
}